Exercicio1/Armazenamento.py
Exercicio1/Consulta.py
Exercicio1/Interacao.py
Exercicio1/__init__.py
Exercicio1-0.0.1.dist-info/LICENSE.txt
Exercicio1-0.0.1.dist-info/METADATA
Exercicio1-0.0.1.dist-info/WHEEL
Exercicio1-0.0.1.dist-info/top_level.txt
Exercicio1-0.0.1.dist-info/RECORD
