Metadata-Version: 2.1
Name: Exercicio1
Version: 0.0.1
Summary: pacote para armazenamento e consulta de dados
Home-page: https://github.com/
Author: Luiz Felipe Pina
Author-email: pina1402@gmail.com
License: MIT License
Keywords: Pacote
License-File: LICENSE.txt
